mkdocs_zettelkasten/plugin/__init__.py
mkdocs_zettelkasten/plugin/adapters/__init__.py
mkdocs_zettelkasten/plugin/adapters/backlinks_to_page.py
mkdocs_zettelkasten/plugin/adapters/page_links_to_zettels.py
mkdocs_zettelkasten/plugin/adapters/page_ref.py
mkdocs_zettelkasten/plugin/adapters/page_title.py
mkdocs_zettelkasten/plugin/adapters/prev_next_page.py
mkdocs_zettelkasten/plugin/entities/__init__.py
mkdocs_zettelkasten/plugin/entities/zettel.py
mkdocs_zettelkasten/plugin/plugin.py
mkdocs_zettelkasten/plugin/services/__init__.py
mkdocs_zettelkasten/plugin/services/backlink_processor.py
mkdocs_zettelkasten/plugin/services/page_transformer.py
mkdocs_zettelkasten/plugin/services/tags_service.py
mkdocs_zettelkasten/plugin/services/zettel_parser.py
mkdocs_zettelkasten/plugin/services/zettel_service.py
mkdocs_zettelkasten/plugin/services/zettel_store.py
mkdocs_zettelkasten/plugin/templates/tags.md.j2
mkdocs_zettelkasten/plugin/utils/__init__.py
mkdocs_zettelkasten/plugin/utils/date_utils.py
mkdocs_zettelkasten/plugin/utils/git_utils.py
mkdocs_zettelkasten/plugin/utils/jinja_utils.py
mkdocs_zettelkasten/plugin/utils/metadata_utils.py
mkdocs_zettelkasten/plugin/utils/patterns.py
mkdocs_zettelkasten/themes/__init__.py
mkdocs_zettelkasten/themes/solarized_light/404.html
mkdocs_zettelkasten/themes/solarized_light/__init__.py
mkdocs_zettelkasten/themes/solarized_light/base.html
mkdocs_zettelkasten/themes/solarized_light/content.html
mkdocs_zettelkasten/themes/solarized_light/css/base.css
mkdocs_zettelkasten/themes/solarized_light/css/bootstrap.min.css
mkdocs_zettelkasten/themes/solarized_light/css/codehilite.css
mkdocs_zettelkasten/themes/solarized_light/css/font-awesome.min.css
mkdocs_zettelkasten/themes/solarized_light/css/solarized-light.css
mkdocs_zettelkasten/themes/solarized_light/fonts/FontAwesome.otf
mkdocs_zettelkasten/themes/solarized_light/fonts/fontawesome-webfont.eot
mkdocs_zettelkasten/themes/solarized_light/fonts/fontawesome-webfont.svg
mkdocs_zettelkasten-0.4.2.dist-info/LICENSE
mkdocs_zettelkasten-0.4.2.dist-info/METADATA
mkdocs_zettelkasten-0.4.2.dist-info/WHEEL
mkdocs_zettelkasten-0.4.2.dist-info/entry_points.txt
mkdocs_zettelkasten-0.4.2.dist-info/RECORD
