Metadata-Version: 2.3
Name: mkdocs-zettelkasten
Version: 0.4.2
Summary: Add Zettelkasten features to MkDocs
License: MIT
Author: Tomáš Bouška
Author-email: tomas@buvis.net
Requires-Python: >=3.9
Classifier: License :: OSI Approved :: MIT License
Classifier: Programming Language :: Python :: 3
Classifier: Programming Language :: Python :: 3.9
Classifier: Programming Language :: Python :: 3.10
Classifier: Programming Language :: Python :: 3.11
Classifier: Programming Language :: Python :: 3.12
Classifier: Programming Language :: Python :: 3.13
Requires-Dist: PyYAML (==6.0.2)
Requires-Dist: colorlog (==6.9.0)
Requires-Dist: gitpython (==3.1.44)
Requires-Dist: jinja2 (==3.1.6)
Requires-Dist: mkdocs (==1.6.1)
Requires-Dist: pymdown-extensions (==10.15)
Requires-Dist: tzlocal (==5.3.1)
